mypackage/__init__.py
mypackage/genetic_library.py
genetic_lib-0.1.1.dist-info/LICENSE
genetic_lib-0.1.1.dist-info/METADATA
genetic_lib-0.1.1.dist-info/WHEEL
genetic_lib-0.1.1.dist-info/top_level.txt
genetic_lib-0.1.1.dist-info/RECORD
